<?xml version="1.0" encoding="utf-8"?>
<!DOCTYPE hibernate-mapping PUBLIC "-//Hibernate/Hibernate Mapping DTD 3.0//EN"
"http://hibernate.sourceforge.net/hibernate-mapping-3.0.dtd">
<!-- 
    Mapping file autogenerated by MyEclipse Persistence Tools
-->
<hibernate-mapping>
    <class name="com.detachment.pojo.TbDepartment" table="Tb_Department" schema="dbo" catalog="detachment">
        <id name="departmentId" type="java.lang.String">
            <column name="departmentId" length="50" />
            <generator class="assigned" />
        </id>
        <property name="region" type="java.lang.String">
            <column name="region" length="50" />
        </property>
        <property name="departmentName" type="java.lang.String">
            <column name="departmentName" length="50" />
        </property>
        <property name="parentId" type="java.lang.String">
            <column name="parentId" length="50" />
        </property>
        <property name="departmentPhone" type="java.lang.String">
            <column name="departmentPhone" length="50" />
        </property>
        <property name="departmentAddress" type="java.lang.String">
            <column name="departmentAddress" length="200" />
        </property>
        <property name="remark" type="java.lang.String">
            <column name="remark" length="50" />
        </property>
        <set name="tbFormalAccidents" inverse="true">
            <key>
                <column name="departmentId" length="50" />
            </key>
            <one-to-many class="com.detachment.pojo.TbFormalAccident" />
        </set>
        <set name="tbUsers" inverse="true">
            <key>
                <column name="departmentId" length="50" />
            </key>
            <one-to-many class="com.detachment.pojo.TbUser" />
        </set>
    </class>
</hibernate-mapping>
